<!DOCTYPE ui:UiBinder SYSTEM "http://dl.google.com/gwt/DTD/xhtml.ent">
<ui:UiBinder xmlns:ui="urn:ui:com.google.gwt.uibinder"
	xmlns:g="urn:import:com.google.gwt.user.client.ui"
	xmlns:b="urn:import:com.google.gwt.user.cellview.client"
	 xmlns:my="urn:import:ch.unibas.medizin.osce.client.style.widgets">
	 
<ui:style src="../styles.css" >
.tabPanel{
	margin-left: 20px;
}
</ui:style>
	<g:HTMLPanel ui:field="containerHTMLPanel" >
	<g:HTMLPanel>
		<g:TabPanel  ui:field="osceTab" width="100%" addStyleNames="{style.tabPanel}" >
			 <!-- <g:Tab>
				<g:TabHTML >OM</g:TabHTML>
				<g:Label>Hello</g:Label>
			</g:Tab> -->
		</g:TabPanel>
	</g:HTMLPanel>
	</g:HTMLPanel>
</ui:UiBinder> 